{
  "variants": {
    "facing=north,counter=0": {
      "model": "minelabs:block/tuberack"
    },
    "facing=east,counter=0": {
      "model": "minelabs:block/tuberack",
      "y": 90
    },
    "facing=south,counter=0": {
      "model": "minelabs:block/tuberack",
      "y": 180
    },
    "facing=west,counter=0": {
      "model": "minelabs:block/tuberack",
      "y": 270
    },
    "facing=north,counter=1": {
      "model": "minelabs:block/tuberack_counter1"
    },
    "facing=east,counter=1": {
      "model": "minelabs:block/tuberack_counter1",
      "y": 90
    },
    "facing=south,counter=1": {
      "model": "minelabs:block/tuberack_counter1",
      "y": 180
    },
    "facing=west,counter=1": {
      "model": "minelabs:block/tuberack_counter1",
      "y": 270
    },
    "facing=north,counter=2": {
      "model": "minelabs:block/tuberack_counter2"
    },
    "facing=east,counter=2": {
      "model": "minelabs:block/tuberack_counter2",
      "y": 90
    },
    "facing=south,counter=2": {
      "model": "minelabs:block/tuberack_counter2",
      "y": 180
    },
    "facing=west,counter=2": {
      "model": "minelabs:block/tuberack_counter2",
      "y": 270
    }
  }
}