{
  "type": "minelabs:ionic_crafting",
  "cation": {
    "structure":
    {
      "atoms": [
        {"key":  "NA1", "atom":  "Na"}
      ],
      "bonds": [
      ]
    },
    "amount": 2,
    "density": 8,
    "charge": 1
  },
  "anion": {
    "structure": {
      "atoms": [
        {
          "key": "S1",
          "atom": "S"
        },
        {
          "key": "O1",
          "atom": "O"
        },
        {
          "key": "O2",
          "atom": "O"
        },
        {
          "key": "O3",
          "atom": "O"
        },
        {
          "key": "O4",
          "atom": "O"
        }
      ],
      "bonds": [
        {
          "from": "O1",
          "to": "S1",
          "bondOrder": 2
        },
        {
          "from": "O2",
          "to": "S1",
          "bondOrder": 2
        },
        {
          "from": "O3",
          "to": "S1",
          "bondOrder": 1
        },
        {
          "from": "O4",
          "to": "S1",
          "bondOrder": 1
        }
      ]
    },
    "amount": 1,
    "density": 8,
    "charge": 2
  },
  "result": {
    "item": "minelabs:erlenmeyer/erlenmeyer_h2o"
  },
  "container": true,
  "time": 23
}